up_jsprit/__init__.py
up_jsprit/config.py
up_jsprit/custom_cost.py
up_jsprit/debug.py
up_jsprit/solve_vrp_problem.py
up_jsprit/up_jsprit.py
up_jsprit/utils.py
up_jsprit/jar/commons-compiler-3.1.2.jar
up_jsprit/jar/commons-configuration-1.9.jar
up_jsprit/jar/commons-io-1.3.1.jar
up_jsprit/jar/commons-lang-2.6.jar
up_jsprit/jar/commons-logging-1.1.1.jar
up_jsprit/jar/commons-math-2.1.jar
up_jsprit/jar/commons-math3-3.4.jar
up_jsprit/jar/graphhopper-core-7.0.jar
up_jsprit/jar/graphhopper-web-api-7.0.jar
up_jsprit/jar/gs-algo-1.3.jar
up_jsprit/jar/gs-core-1.3.jar
up_jsprit/jar/gs-ui-1.3.jar
up_jsprit/jar/hamcrest-core-1.3.jar
up_jsprit/jar/hppc-0.8.1.jar
up_jsprit/jar/jackson-annotations-2.10.5.jar
up_jsprit/jar/jackson-core-2.10.5.jar
up_jsprit/jar/jackson-databind-2.10.5.1.jar
up_jsprit/jar/jackson-dataformat-xml-2.10.5.jar
up_jsprit/jar/jackson-datatype-jts-2.14.jar
up_jsprit/jar/jackson-module-jaxb-annotations-2.10.5.jar
up_jsprit/jar/jakarta.activation-api-1.2.1.jar
up_jsprit/jar/jakarta.xml.bind-api-2.3.2.jar
up_jsprit/jar/janino-3.1.2.jar
up_jsprit/jar/java-util-1.8.3.jar
up_jsprit/jar/jcommon-1.0.23.jar
up_jsprit/jar/jfreechart-1.0.19.jar
up_jsprit/jar/jsprit-analysis-1.9.0-beta.11.jar
up_jsprit/jar/jsprit-core-1.7.jar
up_jsprit/jar/jsprit-core-1.9.0-beta.11.jar
up_jsprit/jar/jsprit-core-1.9.0-beta.4.jar
up_jsprit/jar/jsprit-io-1.9.0-beta.4.jar
up_jsprit/jar/jts-core-1.19.0.jar
up_jsprit/jar/junit-4.12.jar
up_jsprit/jar/logback-classic-1.0.11.jar
up_jsprit/jar/logback-core-1.0.11.jar
up_jsprit/jar/mbox2-1.0.jar
up_jsprit/jar/osmosis-osm-binary-0.47.3.jar
up_jsprit/jar/pherd-1.0.jar
up_jsprit/jar/protobuf-java-3.11.4.jar
up_jsprit/jar/scala-library-2.10.1.jar
up_jsprit/jar/slf4j-api-1.7.21.jar
up_jsprit/jar/slf4j-api-1.7.32.jar
up_jsprit/jar/slf4j-api-1.7.36.jar
up_jsprit/jar/slf4j-api-1.7.7.jar
up_jsprit/jar/stax2-api-4.2.1.jar
up_jsprit/jar/woodstox-core-6.2.1.jar
up_jsprit/jar/xercesImpl-2.12.0.jar
up_jsprit/jar/xml-apis-1.4.01.jar
up_jsprit-1.0.5.dist-info/LICENSE.txt
up_jsprit-1.0.5.dist-info/METADATA
up_jsprit-1.0.5.dist-info/WHEEL
up_jsprit-1.0.5.dist-info/top_level.txt
up_jsprit-1.0.5.dist-info/RECORD
