Metadata-Version: 2.1
Name: up_jsprit
Version: 1.0.5
Summary: Library for Integration of JSprit Toolkit with Unified Planning Library
Home-page: https://github.com/ppablo78/up-jsprit
Author: Paolo Petrinca
Author-email: paolo.petrinca@gmail.com
Classifier: Programming Language :: Python :: 3
License-File: LICENSE.txt
